[{"T":"131","S":"006","A":"70","P":"136","text":"وعذاب اليم بما كانوا يكفرون","textm":"وَعَذَابٌ أَلِيمٌ بِمَا كَانُوا يَكْفُرُونَ ","s_loc":"[619.5, 550.367737, 622.5, 592.358398]","e_loc":"[315, 550.367737, 318, 597.607117]"},{"T":"131","S":"006","A":"124","P":"143","text":"وعذاب شديد بما كانوا يمكرون","textm":"وَعَذَابٌ شَدِيدٌ بِمَا كَانُوا يَمْكُرُونَ ","s_loc":"[537, 117.72142, 540, 162.711365]","e_loc":"[160.5, 125.219627, 163.5, 168.709915]"},{"T":"131","S":"010","A":"4","P":"208","text":"وعذاب اليم بما كانوا يكفرون","textm":"وَعَذَابٌ أَلِيمٌ بِمَا كَانُوا يَكْفُرُونَ ","s_loc":"[614.25, 332.170013, 617.25, 383.158508]","e_loc":"[344.25, 338.918396, 347.25, 382.408691]"} ]