[{"T":"256","S":"16","A":"70","P":"274","text":"لكي لا يعلم بعد علم شيئاً","textm":"لِكَيْ لَا يَعْلَمَ بَعْدَ عِلْمٍ شَيْئًا ","s_loc":"[523.5, 389.906189, 526.5, 432.646667]","e_loc":"[306, 389.156372, 309, 430.397186]"},{"T":"256","S":"22","A":"5","P":"332","text":"لكيلا يعلم بعد علم شيئاً","textm":"لِكَيْلَا يَعْلَمَ مِنْ بَعْدِ عِلْمٍ شَيْئًا ","s_loc":"[291.75, 229.444641, 294.75, 272.934937]","e_loc":"[479.25, 177.707047, 482.25, 221.947159]"},{"T":"256","S":"23","A":"78","P":"347","text":"هو الذي أنشأ لكم السمع والأبصار والأفئدة قليلاً ما تشكرون","textm":"وَهُوَ الَّذِي أَنْشَأَ لَكُمُ السَّمْعَ وَالْأَبْصَارَ وَالْأَفْئِدَةَ قَلِيلًا مَا تَشْكُرُونَ","s_loc":"[419.25, 709.329651, 422.25, 752.070129]","e_loc":"[387.750031, 657.592041, 390.750031, 698.832825]"} ]