[{"T":"103","S":"011","A":"107","P":"180","text":"وإن يمسسك الله بضر فلا كاشف له إلا هو وإن يردك بخير","textm":"وَإِنْ يَمْسَسْكَ اللَّهُ بِضُرٍّ فَلَا كَاشِفَ لَهُ إِلَّا هُوَ وَإِنْ يُرِدْكَ بِخَيْرٍ","s_loc":"[178.415359, 223.433212, 181.415359, 267.670959]","e_loc":"[144.681229, 176.197235, 147.681229, 221.184769]"} ,{"T":"177","S":"010","A":"104","P":"180","text":"قل يا أيها الناس","textm":"قُلْ يَا أَيُّهَا النَّاسُ ","s_loc":"[419.052155, 391.383362, 422.052155, 442.36911]","e_loc":"[314.101532, 398.131348, 317.101532, 436.37088]"} ,{"T":"177","S":"010","A":"108","P":"180","text":"قل يا أيها الناس","textm":"قُلْ يَا أَيُّهَا النَّاسُ ","s_loc":"[513.50769, 92.222176, 516.50769, 134.210602]","e_loc":"[418.30249, 90.722618, 421.30249, 130.461716]"} ,{"T":"384","S":"10","A":"98","P":"180","text":"عذاب الخزي في الحياة الدنيا","textm":"عَذَابَ الْخِزْيِ فِي الْحَيَاةِ الدُّنْيَا ","s_loc":"[513.50769, 714.537415, 516.50769, 754.276489]","e_loc":"[310.353271, 710.788513, 313.353271, 749.777832]"}]