[{"T":"285","S":"27","A":"7","P":"316","text":"إني آنست نارا سآتيكم منها بخبر أو آتيكم بشهاب قبس","textm":"إِنِّي آنَسْتُ نَارًا سَآتِيكُمْ مِنْهَا بِخَبَرٍ أَوْ آتِيكُمْ بِشِهَابٍ قَبَسٍ  ","s_loc":"[374.822968, 709.28894, 377.822968, 749.777832]","e_loc":"[427.298248, 664.302246, 430.298248, 707.040466]"} ,{"T":"314","S":"27","A":"8","P":"316","text":"فلما جاءها نودي أن بورك","textm":"فَلَمَّا جَاءَهَا نُودِيَ أَنْ بُورِكَ  ","s_loc":"[276.619141, 668.051208, 279.619141, 707.040527]","e_loc":"[107.948524, 663.55249, 110.948524, 707.040466]"} ,{"T":"316","S":"27","A":"12","P":"316","text":"إلى فرعون وقومه","textm":"إِلَى فِرْعَوْنَ وَقَوْمِهِ ","s_loc":"[440.791931, 399.63089, 443.791931, 443.868652]","e_loc":"[316.350464, 394.382446, 319.350464, 437.120667]"} ,{"T":"317","S":"27","A":"13","P":"316","text":"هذا سحر مبين","textm":"هَذَا سِحْرٌ مُبِينٌ ","s_loc":"[309.603638, 354.644257, 312.603638, 397.382446]","e_loc":"[205.402664, 355.394043, 208.402664, 395.882904]"} ,{"T":"318","S":"27","A":"13","P":"316","text":"آياتنا مبصرة","textm":"آيَاتُنَا مُبْصِرَةً ","s_loc":"[447.538757, 352.394928, 450.538757, 395.133118]","e_loc":"[347.835663, 355.394043, 350.835663, 396.63269]"}]