[{"T":"285","S":"20","A":"10","P":"260","text":"أمكثوا إني آنست نارا لعلي آتيكم منها بقبس","textm":"امْكُثُوا إِنِّي آنَسْتُ نَارًا لَعَلِّي آتِيكُمْ مِنْهَا بِقَبَسٍ ","s_loc":"[395.81308, 315.655823, 398.81308, 351.646027]","e_loc":"[85.459091, 313.406494, 88.459091, 350.146484]"},{"T":"285","S":"27","A":"7","P":"316","text":"إني آنست نارا سآتيكم منها بخبر أو آتيكم بشهاب قبس","textm":"إِنِّي آنَسْتُ نَارًا سَآتِيكُمْ مِنْهَا بِخَبَرٍ أَوْ آتِيكُمْ بِشِهَابٍ قَبَسٍ  ","s_loc":"[374.822968, 709.28894, 377.822968, 749.777832]","e_loc":"[427.298248, 664.302246, 430.298248, 707.040466]"},{"T":"285","S":"28","A":"29","P":"326","text":"أمكثوا إني آنست نارا لعلي آتيكم منها بخير أو جذوه من النار","textm":"امْكُثُوا إِنِّي آنَسْتُ نَارًا لَعَلِّي آتِيكُمْ مِنْهَا بِخَبَرٍ أَوْ جَذْوَةٍ مِنَ النَّارِ ","s_loc":"[140.932983, 713.787598, 143.932983, 749.028076]","e_loc":"[153.677002, 666.551636, 156.677002, 704.041382]"} ]