[{"T":"365","S":"32","A":"20","P":"349","text":"ذوقوا عذاب النار الذي كنتم به تكذبون","textm":"ذُوقُوا عَذَابَ النَّارِ الَّذِي كُنْتُمْ بِهِ تُكَذِّبُونَ ","s_loc":"[457.284149, 663.552551, 460.284149, 709.289856]","e_loc":"[185.911835, 672.549866, 188.911835, 712.28894]"},{"T":"365","S":"34","A":"42","P":"362","text":"ذوقوا عذاب النار التي كنتم به تكذبون","textm":"ذُوقُوا عَذَابَ النَّارِ الَّتِي كُنْتُمْ بِهَا تُكَذِّبُونَ  ","s_loc":"[443.040863, 96.72084, 446.040863, 135.710144]","e_loc":"[173.917465, 91.472397, 176.917465, 134.210602]"} ]