[{"T":"375","S":"35","A":"38","P":"367","text":"إن الله عالم غيب السماوات والأرض","textm":" إِنَّ اللَّهَ عَالِمُ غَيْبِ السَّمَاوَاتِ وَالْأَرْضِ","s_loc":"[514.257385, 86.973732, 517.257385, 127.462601]","e_loc":"[266.873749, 89.223061, 269.873749, 130.461716]"},{"T":"375","S":"49","A":"18","P":"437","text":"إن الله عالم غيب السماوات والأرض","textm":" إِنَّ اللَّهَ عَالِمُ غَيْبِ السَّمَاوَاتِ وَالْأَرْضِ","s_loc":"[350.834229, 713.787598, 353.834229, 752.776917]","e_loc":"[119.193222, 710.038757, 122.193222, 753.526733]"} ]